tabbed_admin/MANIFEST.in
tabbed_admin/README.rst
tabbed_admin/__init__.py
tabbed_admin/admin.py
tabbed_admin/apps.py
tabbed_admin/models.py
tabbed_admin/requirements.txt
tabbed_admin/settings.py
tabbed_admin/setup.py
tabbed_admin/static/tabbed_admin/css/jquery-ui-1.11.4.min.css
tabbed_admin/static/tabbed_admin/css/tabbed_admin.css
tabbed_admin/static/tabbed_admin/css/tabbed_grappelli_admin.css
tabbed_admin/static/tabbed_admin/css/images/ui-bg_flat_0_aaaaaa_40x100.png
tabbed_admin/static/tabbed_admin/css/images/ui-bg_flat_0_eeeeee_40x100.png
tabbed_admin/static/tabbed_admin/css/images/ui-bg_flat_55_c0402a_40x100.png
tabbed_admin/static/tabbed_admin/css/images/ui-bg_flat_55_eeeeee_40x100.png
tabbed_admin/static/tabbed_admin/css/images/ui-bg_glass_100_f8f8f8_1x400.png
tabbed_admin/static/tabbed_admin/css/images/ui-bg_glass_35_dddddd_1x400.png
tabbed_admin/static/tabbed_admin/css/images/ui-bg_glass_60_eeeeee_1x400.png
tabbed_admin/static/tabbed_admin/css/images/ui-bg_inset-hard_75_999999_1x100.png
tabbed_admin/static/tabbed_admin/css/images/ui-bg_inset-soft_50_c9c9c9_1x100.png
tabbed_admin/static/tabbed_admin/css/images/ui-icons_3383bb_256x240.png
tabbed_admin/static/tabbed_admin/css/images/ui-icons_444444_256x240.png
tabbed_admin/static/tabbed_admin/css/images/ui-icons_454545_256x240.png
tabbed_admin/static/tabbed_admin/css/images/ui-icons_555555_256x240.png
tabbed_admin/static/tabbed_admin/css/images/ui-icons_70b2e1_256x240.png
tabbed_admin/static/tabbed_admin/css/images/ui-icons_777620_256x240.png
tabbed_admin/static/tabbed_admin/css/images/ui-icons_777777_256x240.png
tabbed_admin/static/tabbed_admin/css/images/ui-icons_999999_256x240.png
tabbed_admin/static/tabbed_admin/css/images/ui-icons_cc0000_256x240.png
tabbed_admin/static/tabbed_admin/css/images/ui-icons_fbc856_256x240.png
tabbed_admin/static/tabbed_admin/css/images/ui-icons_ffffff_256x240.png
tabbed_admin/static/tabbed_admin/js/jquery-ui-1.11.4.min.js
tabbed_admin/templates/tabbed_admin/change_form.html
django_tabbed_admin_for_garpixcms-1.1.1.dist-info/METADATA
django_tabbed_admin_for_garpixcms-1.1.1.dist-info/WHEEL
django_tabbed_admin_for_garpixcms-1.1.1.dist-info/top_level.txt
django_tabbed_admin_for_garpixcms-1.1.1.dist-info/RECORD
